file_downloader_mcp/__init__.py
file_downloader_mcp/server.py
file_downloader_mcp-0.1.1.dist-info/METADATA
file_downloader_mcp-0.1.1.dist-info/WHEEL
file_downloader_mcp-0.1.1.dist-info/entry_points.txt
file_downloader_mcp-0.1.1.dist-info/RECORD
