Metadata-Version: 2.4
Name: file-downloader-mcp
Version: 0.1.1
Summary: A simple MCP server for downloading files from URLs
Author-email: Your Name <your.email@example.com>
License: MIT
Requires-Python: >=3.11
Requires-Dist: httpx>=0.25.0
Requires-Dist: mcp>=1.0.0
Provides-Extra: dev
Requires-Dist: pytest-asyncio>=0.21.0; extra == 'dev'
Requires-Dist: pytest>=7.0.0; extra == 'dev'
Requires-Dist: ruff>=0.1.0; extra == 'dev'
